MaybeP2P/__init__.py
MaybeP2P/peer/__init__.py
MaybeP2P/peer/connection.py
MaybeP2P/peer/peer.py
MaybeP2P/peer/peerinfo.py
MaybeP2P/protocol/__init__.py
MaybeP2P/protocol/protocol.py
MaybeP2P/protocol/classicv1/__init__.py
MaybeP2P/protocol/classicv1/message/ERRO.py
MaybeP2P/protocol/classicv1/message/JOIN.py
MaybeP2P/protocol/classicv1/message/LIST.py
MaybeP2P/protocol/classicv1/message/MESG.py
MaybeP2P/protocol/classicv1/message/QUIT.py
MaybeP2P/protocol/classicv1/message/__init__.py
MaybeP2P/protocol/message/REPL.py
MaybeP2P/protocol/message/__init__.py
MaybeP2P/protocol/message/message.py
MaybeP2P-0.0.3.dist-info/METADATA
MaybeP2P-0.0.3.dist-info/RECORD
MaybeP2P-0.0.3.dist-info/WHEEL
MaybeP2P-0.0.3.dist-info/top_level.txt
peer/__init__.py
peer/connection.py
peer/peer.py
protocol/__init__.py
protocol/protocol.py
protocol/classicv1/__init__.py
protocol/classicv1/message/ERRO.py
protocol/classicv1/message/JOIN.py
protocol/classicv1/message/LIST.py
protocol/classicv1/message/MESG.py
protocol/classicv1/message/QUIT.py
protocol/classicv1/message/__init__.py
protocol/message/REPL.py
protocol/message/__init__.py
protocol/message/message.py
