Metadata-Version: 2.1
Name: MaybeP2P
Version: 0.0.3
Summary: Simple solution to implement P2P communication into Applications.
Home-page: https://github.com/jackey8616/MaybeP2P
Author: cl5ode(jackey8616)
Author-email: jackey8616@gmail.com
License: UNKNOWN
Keywords: P2P,peer-to-peer
Platform: UNKNOWN
Classifier: Development Status :: 3 - Alpha
Classifier: Programming Language :: Python :: 2.7
Classifier: Programming Language :: Python :: 3.5
Requires-Python: >=2.7
Requires-Dist: dnspython
